[
    {
        "name": "北海道",
        "romaji": "Hokkaido",
        "hiragana": "ほっかいどう"
    },{
        "name": "青森",
        "romaji": "Aomori",
        "hiragana": "あおもり"
    },{
        "name": "岩手",
        "romaji": "Iwate",
        "hiragana": "いわて"
    }, {
        "name": "宮城",
        "romaji": "Miyagi",
        "hiragana": "みやぎ"
    },{
        "name": "秋田",
        "romaji": "Akita",
        "hiragana": "あきた"
    },{
        "name": "山形",
        "romaji": "Yamagata",
        "hiragana": "やまがた"
    },{
        "name": "福島",
        "romaji": "Fukushima",
        "hiragana": "ふくしま"
    },{
        "name": "茨城",
        "romaji": "Ibaraki",
        "hiragana": "いばらき"
    },{
        "name": "栃木",
        "romaji": "Tochigi",
        "hiragana": "とちぎ"
    },{
        "name": "群馬",
        "romaji": "Gunma",
        "hiragana": "ぐんま"
    },{
        "name": "埼玉",
        "romaji": "Saitama",
        "hiragana": "さいたま"
    },{
        "name": "千葉",
        "romaji": "Chiba",
        "hiragana": "ちば"
    },{
        "name": "東京",
        "romaji": "Tokyo",
        "hiragana": "とうきょう"
    },{
        "name": "神奈川",
        "romaji": "Kanagawa",
        "hiragana": "かながわ"
    },{
        "name": "新潟",
        "romaji": "Niigata",
        "hiragana": "にいがた"
    },{
        "name": "富山",
        "romaji": "Toyama",
        "hiragana": "とやま"
    },{
        "name": "石川",
        "romaji": "Ishikawa",
        "hiragana": "いしかわ"
    },{
        "name": "福井",
        "romaji": "Fukui",
        "hiragana": "ふくい"
    },{
        "name": "山梨",
        "romaji": "Yamanashi",
        "hiragana": "やまなし"
    },{
        "name": "長野",
        "romaji": "Nagano",
        "hiragana": "ながの"
    },{
        "name": "岐阜",
        "romaji": "Gifu",
        "hiragana": "ぎふ"
    },{
        "name": "静岡",
        "romaji": "Shizuoka",
        "hiragana": "しずおか"
    },{
        "name": "愛知",
        "romaji": "Aichi",
        "hiragana": "あいち"
    },{
        "name": "三重",
        "romaji": "Mie",
        "hiragana": "みえ"
    },{
        "name": "滋賀",
        "romaji": "Shiga",
        "hiragana": "しが"
    },{
        "name": "京都",
        "romaji": "Kyoto",
        "hiragana": "きょうと"
    },{
        "name": "大阪",
        "romaji": "Osaka",
        "hiragana": "おおさか"
    },{
        "name": "兵庫",
        "romaji": "Hyogo",
        "hiragana": "ひょうご"
    },{
        "name": "奈良",
        "romaji": "Nara",
        "hiragana": "なら"
    },{
        "name": "和歌山",
        "romaji": "Wakayama",
        "hiragana": "わかやま"
    },{
        "name": "鳥取",
        "romaji": "Tottori",
        "hiragana": "とっとり"
    },{
        "name": "島根",
        "romaji": "Shimane",
        "hiragana": "しまね"
    },{
        "name": "岡山",
        "romaji": "Okayama",
        "hiragana": "おかやま"
    },{
        "name": "広島",
        "romaji": "Hiroshima",
        "hiragana": "ひろしま"
    },{
        "name": "山口",
        "romaji": "Yamaguchi",
        "hiragana": "やまぐち"
    },{
        "name": "徳島",
        "romaji": "Tokushima",
        "hiragana": "とくしま"
    },{
        "name": "香川",
        "romaji": "Kagawa",
        "hiragana": "かがわ"
    },{
        "name": "愛媛",
        "romaji": "Ehime",
        "hiragana": "えひめ"
    },{
        "name": "高知",
        "romaji": "Kochi",
        "hiragana": "こうち"
    },{
        "name": "福岡",
        "romaji": "Fukuoka",
        "hiragana": "ふくおか"
    },{
        "name": "佐賀",
        "romaji": "Saga",
        "hiragana": "さが"
    },{
        "name": "長崎",
        "romaji": "Nagasaki",
        "hiragana": "ながさき"
    },{
        "name": "熊本",
        "romaji": "Kumamoto",
        "hiragana": "くまもと"
    },{
        "name": "大分",
        "romaji": "Oita",
        "hiragana": "おおいた"
    },{
        "name": "宮崎",
        "romaji": "Miyazaki",
        "hiragana": "みやざき"
    },{
        "name": "鹿児島",
        "romaji": "Kagoshima",
        "hiragana": "かごしま"
    },{
        "name": "沖縄",
        "romaji": "Okinawa",
        "hiragana": "おきなわ"
    }
]